Metadata-Version: 1.2
Name: little-boxes
Version: 0.1.0
Summary: Tiny ActivityPub framework written in Python, both database and server agnostic.
Home-page: https://github.com/tsileo/little-boxes
Author: Thomas Sileo
Author-email: t@a4.io
License: ISC
Platform: UNKNOWN
Classifier: Development Status :: 3 - Alpha
Classifier: License :: OSI Approved :: ISC License (ISCL)
Classifier: Programming Language :: Python
Classifier: Programming Language :: Python :: 3.6
Classifier: Programming Language :: Python :: Implementation :: CPython
Classifier: Programming Language :: Python :: Implementation :: PyPy
Requires-Python: >=3.6.0
